django_admin_listfilter_dropdown/__init__.py
django_admin_listfilter_dropdown/filters.py
django_admin_listfilter_dropdown/templates/django_admin_listfilter_dropdown/dropdown_filter.html
django_admin_list_filter_dropdown-1.0.2.dist-info/LICENSE
django_admin_list_filter_dropdown-1.0.2.dist-info/METADATA
django_admin_list_filter_dropdown-1.0.2.dist-info/WHEEL
django_admin_list_filter_dropdown-1.0.2.dist-info/top_level.txt
django_admin_list_filter_dropdown-1.0.2.dist-info/RECORD
