Metadata-Version: 1.1
Name: django-admin-list-filter-dropdown
Version: 1.0.2
Summary: Use dropdowns in Django admin list filter
Home-page: https://github.com/mrts/django-admin-list-filter-dropdown
Author: Mart Sõmermaa
Author-email: mrts.pydev@gmail.com
License: MIT License
Download-URL: https://github.com/mrts/django-admin-list-filter-dropdown/archive/1.0.2.zip
Keywords: django,admin,filter,dropdown
Platform: UNKNOWN
Classifier: Environment :: Web Environment
Classifier: Framework :: Django
Classifier: Intended Audience :: Developers
Classifier: License :: OSI Approved :: MIT License
Classifier: Operating System :: OS Independent
Classifier: Programming Language :: Python
Classifier: Topic :: Internet :: WWW/HTTP
Classifier: Topic :: Internet :: WWW/HTTP :: Dynamic Content
